[
  {
    "id": 5759203,
    "geometry": {
      "type": "Polygon",
      "coordinates": [
        [
          [
            45.999842,
            38.640554
          ],
          [
            45.459705,
            38.185667
          ],
          [
            45.439483,
            37.618546
          ],
          [
            45.855296,
            37.282066
          ],
          [
            46.049265,
            36.48731
          ],
          [
            47.026971,
            36.65058
          ],
          [
            48.839521,
            36.226188
          ],
          [
            48.053021,
            37.63091
          ],
          [
            47.789294,
            38.564632
          ],
          [
            45.999842,
            38.640554
          ]
        ]
      ]
    },
    "code": "2",
    "label": "لیبل دوم"
  },
  {
    "id": 7552168,
    "geometry": {
      "type": "Polygon",
      "coordinates": [
        [
          [
            49.206851,
            34.201764
          ],
          [
            48.98714,
            33.471447
          ],
          [
            50.34935,
            33.434768
          ],
          [
            51.447907,
            34.092615
          ],
          [
            50.569061,
            34.781504
          ],
          [
            49.206851,
            34.201764
          ]
        ]
      ]
    },
    "code": "4",
    "label": "لیبل سوم"
  },
  {
    "id": 8355763,
    "geometry": {
      "type": "Polygon",
      "coordinates": [
        [
          [
            53.959958,
            35.976028
          ],
          [
            53.696286,
            34.829477
          ],
          [
            54.88281,
            34.540301
          ],
          [
            55.541989,
            35.726615
          ],
          [
            53.959958,
            35.976028
          ]
        ]
      ]
    },
    "code": "1",
    "label": "1"
  }
]